cookiecutter_cruft_poetry_tox_pre_commit_ci_cd_instance/__init__.py
cookiecutter_cruft_poetry_tox_pre_commit_ci_cd_instance/entrypoint
cookiecutter_cruft_poetry_tox_pre_commit_ci_cd_instance/example.ipynb
cookiecutter_cruft_poetry_tox_pre_commit_ci_cd_instance/main.py
cookiecutter_cruft_poetry_tox_pre_commit_ci_cd_instance/py.typed
40650d10964ba08ce48c__mypyc.cpython-39-x86_64-linux-gnu.so
cookiecutter_cruft_poetry_tox_pre_commit_ci_cd_instance/__init__.cpython-39-x86_64-linux-gnu.so
cookiecutter_cruft_poetry_tox_pre_commit_ci_cd_instance/main.cpython-39-x86_64-linux-gnu.so
cookiecutter_cruft_poetry_tox_pre_commit_ci_cd_instance-0.0.3.dist-info/entry_points.txt
cookiecutter_cruft_poetry_tox_pre_commit_ci_cd_instance-0.0.3.dist-info/LICENSE
cookiecutter_cruft_poetry_tox_pre_commit_ci_cd_instance-0.0.3.dist-info/WHEEL
cookiecutter_cruft_poetry_tox_pre_commit_ci_cd_instance-0.0.3.dist-info/METADATA
cookiecutter_cruft_poetry_tox_pre_commit_ci_cd_instance-0.0.3.dist-info/RECORD
