Metadata-Version: 2.1
Name: cookiecutter-cruft-poetry-tox-pre-commit-ci-cd-instance
Version: 0.0.3
Summary: Cookiecutter Cruft Poetry Tox Pre Commit Ci Cd Instance
Home-page: https://github.com/TeoZosa/cookiecutter-cruft-poetry-tox-pre-commit-ci-cd-instance
License: Apache-2.0
Author: YOUR_FIRST_AND_LAST_NAME
Author-email: action@github.com
Requires-Python: >=3.8,<3.12
Classifier: Intended Audience :: Developers
Classifier: License :: OSI Approved :: Apache Software License
Classifier: Natural Language :: English
Classifier: Operating System :: OS Independent
Classifier: Programming Language :: Python
Classifier: Programming Language :: Python :: 3
Classifier: Programming Language :: Python :: 3.8
Classifier: Programming Language :: Python :: 3.9
Classifier: Programming Language :: Python :: 3.10
Classifier: Programming Language :: Python :: 3.11
Classifier: Programming Language :: Python :: 3
Classifier: Programming Language :: Python :: 3.10
Classifier: Programming Language :: Python :: 3.11
Classifier: Programming Language :: Python :: 3.8
Classifier: Programming Language :: Python :: 3.9
Classifier: Programming Language :: Python :: Implementation :: CPython
Classifier: Topic :: Software Development :: Libraries :: Python Modules
Requires-Dist: importlib-metadata (>=5.0.0,<6.0.0)
Requires-Dist: jupyter (>=1.0.0,<2.0.0)
Requires-Dist: matplotlib (>=3.6.2,<4.0.0)
Requires-Dist: python-dotenv (>=0.21.0,<0.22.0)
Requires-Dist: rich (>=12.5.1,<13.0.0)
Requires-Dist: sentry-sdk (>=1.11.0,<2.0.0)
Requires-Dist: structlog-sentry-logger (>=0.18.0,<0.19.0)
Requires-Dist: typeguard (>=2.13.3,<3.0.0)
Requires-Dist: typer[all] (>=0.4,<0.7)
Project-URL: Changelog, https://github.com/TeoZosa/cookiecutter-cruft-poetry-tox-pre-commit-ci-cd-instance/releases
Project-URL: Repository, https://github.com/TeoZosa/cookiecutter-cruft-poetry-tox-pre-commit-ci-cd-instance
